{
  "permalink": "/projects/phenix",
  "source": "@site/projects/2019-03-01-phenix/index.md",
  "title": "Phénix",
  "description": "Offrir une seconde vie aux invendus alimentaires",
  "date": "2019-03-01T00:00:00.000Z",
  "formattedDate": "March 1, 2019",
  "tags": [
    {
      "label": "Saison 5",
      "permalink": "/projects/tags/saison-5"
    },
    {
      "label": "Environnement",
      "permalink": "/projects/tags/environnement"
    },
    {
      "label": "Alimentaire",
      "permalink": "/projects/tags/alimentaire"
    }
  ],
  "readingTime": 0.23,
  "truncated": false,
  "authors": [],
  "prevItem": {
    "title": "Liris",
    "permalink": "/projects/liris"
  },
  "nextItem": {
    "title": "Transplant",
    "permalink": "/projects/transplant"
  }
}