{
  "permalink": "/projects/jogl",
  "source": "@site/projects/2020-09-01-jogl/index.md",
  "title": "JOGL",
  "description": "",
  "date": "2020-09-01T00:00:00.000Z",
  "formattedDate": "September 1, 2020",
  "tags": [
    {
      "label": "Saison 8",
      "permalink": "/projects/tags/saison-8"
    },
    {
      "label": "Santé",
      "permalink": "/projects/tags/sante"
    },
    {
      "label": "Science",
      "permalink": "/projects/tags/science"
    },
    {
      "label": "Open Innovation",
      "permalink": "/projects/tags/open-innovation"
    },
    {
      "label": "Matching",
      "permalink": "/projects/tags/matching"
    },
    {
      "label": "sdg09",
      "permalink": "/projects/tags/sdg-09"
    },
    {
      "label": "sdg17",
      "permalink": "/projects/tags/sdg-17"
    }
  ],
  "readingTime": 0.23,
  "truncated": false,
  "authors": [],
  "prevItem": {
    "title": "ImpactScore",
    "permalink": "/projects/impactscore"
  },
  "nextItem": {
    "title": "Mednum",
    "permalink": "/projects/mednum"
  }
}